<toolSet name="External Tools">
  <tool name="Source" showInMainMenu="false" showInEditor="false" showInProject="false" showInSearchPopup="false" disabled="false" useConsole="true" showConsoleOnStdOut="false" showConsoleOnStdErr="false" synchronizeAfterRun="true">
    <exec>
      <option name="COMMAND" value="bash" />
      <option name="PARAMETERS" value="-c &quot;source .env&quot;" />
      <option name="WORKING_DIRECTORY" value="$ProjectFileDir$" />
    </exec>
  </tool>
  <tool name="Start db" showInMainMenu="false" showInEditor="false" showInProject="false" showInSearchPopup="false" disabled="true" useConsole="true" showConsoleOnStdOut="false" showConsoleOnStdErr="false" synchronizeAfterRun="true">
    <exec>
      <option name="COMMAND" value="$USER_HOME$/dev/nexsis/nexsis/lib/with-test-pg" />
      <option name="PARAMETERS" />
      <option name="WORKING_DIRECTORY" value="$USER_HOME$/dev/nexsis/nexsis/lib" />
    </exec>
  </tool>
</toolSet>